CHANGES.rst
MANIFEST.in
README.rst
setup.py
version.txt
src/arstecnica.raccoon.autobahn.egg-info/PKG-INFO
src/arstecnica.raccoon.autobahn.egg-info/SOURCES.txt
src/arstecnica.raccoon.autobahn.egg-info/dependency_links.txt
src/arstecnica.raccoon.autobahn.egg-info/namespace_packages.txt
src/arstecnica.raccoon.autobahn.egg-info/requires.txt
src/arstecnica.raccoon.autobahn.egg-info/top_level.txt
src/arstecnica/raccoon/autobahn/__init__.py
src/arstecnica/raccoon/autobahn/client.py
src/arstecnica/raccoon/autobahn/serializer.py