Metadata-Version: 1.1
Name: arstecnica.raccoon.autobahn
Version: 0.2
Summary: A set of common utilities over Autobahn
Home-page: https://gitlab.com/arstecnica/arstecnica.raccoon.autobahn
Author: Lele Gaifax
Author-email: lele@metapensiero.it
License: GPLv3+
Platform: UNKNOWN
Classifier: Development Status :: 2 - Pre-Alpha
Classifier: Programming Language :: Python
Classifier: Programming Language :: Python :: 3
Classifier: Programming Language :: Python :: 3.5
